adnap/__init__.py
adnap/evaluate.py
adnap/optimize.py
adnap/panda_param.py
adnap-0.3.0.dist-info/METADATA
adnap-0.3.0.dist-info/WHEEL
adnap-0.3.0.dist-info/entry_points.txt
adnap-0.3.0.dist-info/licenses/LICENSE
adnap-0.3.0.dist-info/RECORD
