Metadata-Version: 2.1
Name: adnap
Version: 0.3.0
Summary: Reverse engineer the Panda dynamics model.
Project-URL: homepage, https://github.com/JeanElsner/adnap
Project-URL: documentation, https://adnap.readthedocs.io
Project-URL: repository, https://github.com/JeanElsner/adnap
Author-email: Jean Elsner <jean.elsner@tum.de>
License: MIT License
License-File: LICENSE
Keywords: control,dynamics,emika,franka,jacobian,libfranka,model,panda,python,robot-manipulator,robotics,simulation
Classifier: Intended Audience :: Developers
Classifier: Intended Audience :: Science/Research
Classifier: License :: OSI Approved :: MIT License
Classifier: Programming Language :: Python :: 3.7
Classifier: Programming Language :: Python :: 3.8
Classifier: Programming Language :: Python :: 3.9
Classifier: Programming Language :: Python :: 3.10
Classifier: Programming Language :: Python :: 3.11
Classifier: Topic :: Scientific/Engineering
Requires-Python: >=3.7
Requires-Dist: numpy
Requires-Dist: panda-model
Requires-Dist: roboticstoolbox-python
Requires-Dist: scipy
Requires-Dist: spatialmath-python
Requires-Dist: sympy
Provides-Extra: test
Requires-Dist: anybadge; extra == 'test'
Requires-Dist: pylint; extra == 'test'
Requires-Dist: pylint-exit; extra == 'test'
Requires-Dist: pytest; extra == 'test'
Requires-Dist: pytest-cov; extra == 'test'
